fenil_bubble_sort/__init__.py
fenil_bubble_sort/bubble.py
fen_bubble_sort-0.1.1.dist-info/METADATA
fen_bubble_sort-0.1.1.dist-info/WHEEL
fen_bubble_sort-0.1.1.dist-info/top_level.txt
fen_bubble_sort-0.1.1.dist-info/RECORD
