Metadata-Version: 2.4
Name: fen-bubble-sort
Version: 0.1.1
Summary: A simple bubble sort implementation
Author: Fenil
Classifier: Programming Language :: Python :: 3
Classifier: License :: OSI Approved :: MIT License
Classifier: Operating System :: OS Independent
Requires-Python: >=3.6
Dynamic: author
Dynamic: classifier
Dynamic: requires-python
Dynamic: summary
